scrapy_influxdb_exporter/__init__.py
scrapy_influxdb_exporter/exceptions.py
scrapy_influxdb_exporter/statscollectors.py
scrapy_influxdb_exporter-1.4.0.dist-info/METADATA
scrapy_influxdb_exporter-1.4.0.dist-info/WHEEL
scrapy_influxdb_exporter-1.4.0.dist-info/licenses/LICENSE
scrapy_influxdb_exporter-1.4.0.dist-info/RECORD
