Metadata-Version: 2.4
Name: scrapy-influxdb-exporter
Version: 1.4.0
Summary: Export Scrapy spider stats to InfluxDB.
Project-URL: Homepage, https://github.com/stefanofusai/scrapy-influxdb-exporter
Project-URL: Repository, https://github.com/stefanofusai/scrapy-influxdb-exporter
Author-email: Stefano Fusai <stefanofusai@gmail.com>
Maintainer-email: Stefano Fusai <stefanofusai@gmail.com>
License-File: LICENSE
Requires-Python: >=3.12
Requires-Dist: influxdb3-python<1.0.0,>=0.4.0
Requires-Dist: scrapy<3.0.0,>=2.10.0
